{
  "category": "PROJECT-ZERO-AUTHOR",
  "description": "Cluster designed for tagging OSINT artifacts with relevant Google Project Zero author information. Open-source intelligence (OSINT) is data collected from publicly available sources to be used in an intelligence context. In the intelligence community, the term open refers to overt, publicly available sources (as opposed to covert or clandestine sources). It is not related to open-source software or collective intelligence.",
  "name": "OSRS Project Zero Author Index",
  "source": "OSRS DEV",
  "type": "OSRS-CMCF-BLOCK-H",
  "uuid": "feda733c-2817-11ea-978f-2e728ce88125",
  "values": [
	{
      "description": "Security researcher and vulnerability author.",
      "meta": {
	  "kill_chain": [
          "author-source:Project Zero Author"
        ],
        "refs": [
          "aaron@securitymetrics.com"
        ]
      },
      "uuid": "e0a899a0-28b9-11ea-978f-2e728ce88125",
      "value": "OSRS CVE Author Index: Aaron Bishop"
    },

    {
      "description": "Security researcher and CVE author. Information Security Specialist - Intern at Trend Micro.",
      "meta": {
	  "kill_chain": [
          "author-source:Project Zero Author"
        ],
        "refs": [
          "https://www.linkedin.com/in/ashishvermarox/",
		  "https://twitter.com/ashishvermarox"
        ],
		"synonyms": [
		"@ashishvermarox"
		]
      },
      "uuid": "b59dc158-2d88-11ea-978f-2e728ce88125",
      "value": "OSRS CVE Author Index: Ashish Verma"
    }
	  ],
	"version": 1
}
